oasm_sdk/__init__.py
oasm_sdk/client.py
oasm_sdk/core.py
oasm_sdk/exceptions.py
oasm_sdk/models.py
oasm_sdk/worker.py
oasm_sdk-0.1.3.dist-info/licenses/LICENSE
oasm_sdk-0.1.3.dist-info/METADATA
oasm_sdk-0.1.3.dist-info/WHEEL
oasm_sdk-0.1.3.dist-info/top_level.txt
oasm_sdk-0.1.3.dist-info/RECORD
