Metadata-Version: 2.4
Name: oasm-sdk
Version: 0.1.3
Summary: Python SDK for OASM platform
Home-page: https://github.com/oasm/oasm-sdk-python
Author: OASM
Author-email: tuanthanh2kk4@gmail.com
Classifier: Programming Language :: Python :: 3
Classifier: License :: OSI Approved :: MIT License
Classifier: Operating System :: OS Independent
Requires-Python: >=3.8
License-File: LICENSE
Requires-Dist: requests>=2.31.0
Requires-Dist: urllib3>=1.26.0
Dynamic: author
Dynamic: author-email
Dynamic: classifier
Dynamic: description
Dynamic: description-content-type
Dynamic: home-page
Dynamic: license-file
Dynamic: requires-dist
Dynamic: requires-python
Dynamic: summary
